.codeclimate.yml
.coveragerc
.gitignore
.pylintrc
.travis.yml
Dockerfile
LICENSE
MANIFEST.in
README.md
README.rst
docker-compose.yml
requirements.txt
screenshot.png
setup.cfg
setup.py
.github/ISSUE_TEMPLATE.md
.github/PULL_REQUEST_TEMPLATE.md
Orange3_Datasets.egg-info/PKG-INFO
Orange3_Datasets.egg-info/SOURCES.txt
Orange3_Datasets.egg-info/dependency_links.txt
Orange3_Datasets.egg-info/entry_points.txt
Orange3_Datasets.egg-info/namespace_packages.txt
Orange3_Datasets.egg-info/not-zip-safe
Orange3_Datasets.egg-info/requires.txt
Orange3_Datasets.egg-info/top_level.txt
doc/Makefile
doc/source/about.rst
doc/source/conf.py
doc/source/contributing.rst
doc/source/index.rst
doc/source/installation.rst
doc/source/usage_cli.rst
doc/source/usage_gui.rst
doc/widgets/mywidget.md
doc/widgets/icons/mywidget.png
orangecontrib/__init__.py
orangecontrib/datasets/__init__.py
orangecontrib/datasets/api_wrapper.py
orangecontrib/datasets/countries.py
orangecontrib/datasets/countries_and_regions.py
orangecontrib/datasets/indicators_list.py
orangecontrib/datasets/owwidget_base.py
orangecontrib/datasets/tutorials/__init__.py
orangecontrib/datasets/tutorials/example_tutorial.ows
orangecontrib/datasets/widgets/__init__.py
orangecontrib/datasets/widgets/owworldbankclimate.py
orangecontrib/datasets/widgets/owworldbankindicators.py
orangecontrib/datasets/widgets/icons/UNComtrade.svg
orangecontrib/datasets/widgets/icons/category.svg
orangecontrib/datasets/widgets/icons/climate.png
orangecontrib/datasets/widgets/icons/cloud.svg
orangecontrib/datasets/widgets/icons/mywidget.svg
orangecontrib/datasets/widgets/icons/wb_icon.png
orangecontrib/datasets/widgets/tests/__init__.py
orangecontrib/datasets/widgets/tests/test_owworldbankindicators.py
provision/docker/docker.bashrc