Metadata-Version: 1.1
Name: Orange3-Datasets
Version: 0.1.5
Summary: Orange interface for World Bank Data Indicator and Climate APIs
Home-page: https://github.com/biolab/orange3-datasets
Author: Miha Zidar
Author-email: zidarsk8@gmail.com
License: MIT
Download-URL: https://github.com/biolab/orange3-datasets/tarball/0.1.5
Keywords: orange3 add-on,world bank data,indicator api
Platform: UNKNOWN
Classifier: Development Status :: 4 - Beta
Classifier: Environment :: X11 Applications :: Qt
Classifier: Environment :: Plugins
Classifier: Programming Language :: Python
Classifier: Operating System :: OS Independent
Classifier: Topic :: Scientific/Engineering :: Artificial Intelligence
Classifier: Topic :: Scientific/Engineering :: Visualization
Classifier: Topic :: Software Development :: Libraries :: Python Modules
Classifier: Intended Audience :: Education
Classifier: Intended Audience :: Science/Research
Classifier: Intended Audience :: Developers
